[
  {
    "Placement": "wh1",
    "Gender": "women",
    "Device": "desktop",
    "Image": "https://static-sg.zacdn.com/cms/DY/Mar2017/SEGMENT_HERO_996x500-internationalwomensday2.jpg",
    "Exit Url": "/women/zalora-anniversary/",
    "Headline": "NA",
    "Subline": "NA",
    "EventLabel": "TRE|NA|5thAnnivMar|ALL|NA|"
  },
  {
    "Placement": "wn1",
    "Gender": "women",
    "Device": "desktop",
    "Image": "https://static-sg.zacdn.com/cms/DY/Mar2017/N1_NEWARRIVALS_360x420-clarksmarch-women.jpg",
    "Exit Url": "/women/clarks",
    "Headline": "Clarks",
    "Subline": "Classic shoes built with the finest craftsmanship and comfort.",
    "EventLabel": "NewA|WS|wsclarksss17|ALL|NA|ZAP"
  },
  {
    "Placement": "wn2",
    "Gender": "women",
    "Device": "desktop",
    "Image": "https://static-sg.zacdn.com/cms/DY/Mar2017/N2_NEWARRIVALS_620x420-safari-women.jpg",
    "Exit Url": "/women/all-products/?cmpgn_one=safarianddesert",
    "Headline": "Safari Traveller",
    "Subline": "Awaken your senses with a selection of desert tones and safari accents.",
    "EventLabel": "TRE|Women|SafariTravellerandDesertMystic|ALL|NA"
  },
  {
    "Placement": "wcu1",
    "Gender": "women",
    "Device": "desktop",
    "Image": "https://static-sg.zacdn.com/cms/DY/Mar2017/N2_NEWARRIVALS_620x420-rplpricebucket-women.jpg",
    "Exit Url": "/women/all-products/?sort=popularity&price=1-39.99",
    "Headline": "Spring Steals Below $40",
    "Subline": "Get a whole lot more out of your next shopping spree.",
    "EventLabel": "SAL|Women|wpricepointMar|ALL|NA"
  },
  {
    "Placement": "wcu2",
    "Gender": "women",
    "Device": "desktop",
    "Image": "https://static-sg.zacdn.com/cms/DY/Mar2017/N1_NEWARRIVALS_360x420-sunglasses-women.jpg",
    "Exit Url": "/women/accessories/sunglasses/",
    "Headline": "Finding The Right Shades",
    "Subline": "Sunglasses that open your eyes to a whole new world.",
    "EventLabel": "CAT|WA|EyewearPushMarch2017|ALL|NA|"
  },
  {
    "Placement": "wcu3",
    "Gender": "women",
    "Device": "desktop",
    "Image": "https://static-sg.zacdn.com/cms/DY/Mar2017/N1_NEWARRIVALS_360x420-beautyspotlight-women.jpg",
    "Exit Url": "/women/beauty/new-products/",
    "Headline": "Beauty Spotlight",
    "Subline": "Spring’s latest makeup palettes and more, from the brands you’ll love.",
    "EventLabel": "CAT|WBE|BeautyNewAMarch2017|ALL|NA|"
  },
  {
    "Placement": "wcu4",
    "Gender": "women",
    "Device": "desktop",
    "Image": "https://static-sg.zacdn.com/cms/DY/Mar2017/N2_NEWARRIVALS_620x420-croptops-women.jpg",
    "Exit Url": "/women/all-products/?cmpgn_one=StreetStyleCropTop",
    "Headline": "STREET STYLE HIGHLIGHTS",
    "Subline": "Get the latest on the crop top craze that’s been heating up fashion weeks.",
    "EventLabel": "TRE|Women|StreetStyleCropTops|ALL|NA"
  },
  {
    "Placement": "wfb1",
    "Gender": "women",
    "Device": "desktop",
    "Image": "https://static-sg.zacdn.com/cms/DY/Mar2017/B1-6_322x165-aldomarch-women.jpg",
    "Exit Url": "/women/aldo/",
    "Headline": "NA",
    "Subline": "NA",
    "EventLabel": "NewA|WS|aldomar|ALL|NA"
  },
  {
    "Placement": "wfb2",
    "Gender": "women",
    "Device": "desktop",
    "Image": "https://static-sg.zacdn.com/cms/DY/Mar2017/B1-6_322x165-mangomarch-women.jpg",
    "Exit Url": "/women/mango-shop/",
    "Headline": "NA",
    "Subline": "NA",
    "EventLabel": "NewA|WC-WB-WS|wcwbwsmangoss17|ALL|NA"
  },
  {
    "Placement": "wfb3",
    "Gender": "women",
    "Device": "desktop",
    "Image": "https://static-sg.zacdn.com/cms/DY/Mar2017/B1-6_322x165-underarmourmarch-women.jpg",
    "Exit Url": "/under-armour-shop/",
    "Headline": "NA",
    "Subline": "NA",
    "EventLabel": "NA-BRA|WSP|wunderarmourss17|ALL|NA|under-armour"
  },
  {
    "Placement": "wfb4",
    "Gender": "women",
    "Device": "desktop",
    "Image": "https://static-sg.zacdn.com/cms/DY/Mar2017/B1-6_322x165-warehousemarch-women.jpg",
    "Exit Url": "/warehouse-shop/",
    "Headline": "NA",
    "Subline": "NA",
    "EventLabel": "BRA|WC|wwarehousexmas|ALL|NA|warehouse"
  },
  {
    "Placement": "wfb5",
    "Gender": "women",
    "Device": "desktop",
    "Image": "https://static-sg.zacdn.com/cms/DY/Mar2017/B1-6_322x165-zaloramarch-women.jpg",
    "Exit Url": "/women/zalora/",
    "Headline": "NA",
    "Subline": "NA",
    "EventLabel": "NewA|NA|zaloramar|ALL|NA"
  },
  {
    "Placement": "wfb6",
    "Gender": "women",
    "Device": "desktop",
    "Image": "https://static-sg.zacdn.com/cms/DY/Mar2017/B1-6_322x165-sulwhasoomarch-women.jpg",
    "Exit Url": "/sulwhasoo-shop",
    "Headline": "NA",
    "Subline": "NA",
    "EventLabel": "BRA|WBE|wbesulwhasooss17|ALL|NA|sulwhasoo-shop"
  },
  {
    "Placement": "wc1",
    "Gender": "women",
    "Device": "desktop",
    "Image": "https://static-sg.zacdn.com/cms/DY/Mar2017/C1245_300x198-topsmarch-women.jpg",
    "Exit Url": "/women/clothing/fashion-tops/",
    "Headline": "NA",
    "Subline": "Shop Tops >",
    "EventLabel": "SUB|WC|topsswomen|ALL|NA"
  },
  {
    "Placement": "wc2",
    "Gender": "women",
    "Device": "desktop",
    "Image": "https://static-sg.zacdn.com/cms/DY/Mar2017/C1245_300x198-flatsmarch-women.jpg",
    "Exit Url": "/women/shoes/flats/",
    "Headline": "NA",
    "Subline": "Shop Flats >",
    "EventLabel": "SUB|WS|shoesswomen|ALL|NA"
  },
  {
    "Placement": "wc3",
    "Gender": "women",
    "Device": "desktop",
    "Image": "https://static-sg.zacdn.com/cms/DY/Mar2017/C3_375x500-dressesmarch-women.jpg",
    "Exit Url": "/women/clothing/dresses/",
    "Headline": "NA",
    "Subline": "Shop Dresses >",
    "EventLabel": "SUB|WC|dressesswomen|ALL|NA"
  },
  {
    "Placement": "wc4",
    "Gender": "women",
    "Device": "desktop",
    "Image": "https://static-sg.zacdn.com/cms/DY/Mar2017/C1245_300x198-bagsmarch-women.jpg",
    "Exit Url": "/women/bags/",
    "Headline": "NA",
    "Subline": "Shop Bags >",
    "EventLabel": "SUB|WB|bagswomen|ALL|NA"
  },
  {
    "Placement": "wc5",
    "Gender": "women",
    "Device": "desktop",
    "Image": "https://static-sg.zacdn.com/cms/DY/Mar2017/C1245_300x198-accemarch-women.jpg",
    "Exit Url": "/women/accessories/",
    "Headline": "NA",
    "Subline": "Shop Accessories >",
    "EventLabel": "SUB|WA|accessorieswomen|ALL|NA"
  },
  {
    "Placement": "mh1",
    "Gender": "men",
    "Device": "desktop",
    "Image": "https://static-sg.zacdn.com/cms/DY/Mar2017/SEGMENT_HERO_996x500-zaloraanniv-men.jpg",
    "Exit Url": "/men/zalora-anniversary/",
    "Headline": "NA",
    "Subline": "NA",
    "EventLabel": "TRE|Men|5thAnnivMar|ALL|NA"
  },
  {
    "Placement": "mn1",
    "Gender": "men",
    "Device": "desktop",
    "Image": "https://static-sg.zacdn.com/cms/DY/Mar2017/N1_360x420-shoesunder80-men.jpg",
    "Exit Url": "/men/all-products/?cmpgn_one=shoesforlessthan80&price=1-80",
    "Headline": "Shoes Under $80",
    "Subline": "Grab all the shoes you need - for less.",
    "EventLabel": "SAL|MS-|menshoesunder80|ALL|maxs|"
  },
  {
    "Placement": "mn2",
    "Gender": "men",
    "Device": "desktop",
    "Image": "https://static-sg.zacdn.com/cms/DY/Mar2017/N2_NEWARRIVALS_620x420-polostees17-men.jpg",
    "Exit Url": "/men/all-products/?cmpgn_one=polosandtees17",
    "Headline": "Polos & Tees",
    "Subline": "Get back to basics with our wide selection of essential tops.",
    "EventLabel": "CAT|MC|PolosandTeesMarch2017|ALL|NA|"
  },
  {
    "Placement": "mfb1",
    "Gender": "men",
    "Device": "desktop",
    "Image": "https://static-sg.zacdn.com/cms/DY/Mar2017/B1-6_322x165-underarmourmarch-men.jpg",
    "Exit Url": "/under-armour-shop/?from=men",
    "Headline": "NA",
    "Subline": "NA",
    "EventLabel": "NA-BRA|WSP|wunderarmourss17|ALL|NA|under-armour"
  },
  {
    "Placement": "mfb2",
    "Gender": "men",
    "Device": "desktop",
    "Image": "https://static-sg.zacdn.com/cms/DY/Mar2017/B1_322x165-herschelmarch-men.jpg",
    "Exit Url": "/men/herschel",
    "Headline": "NA",
    "Subline": "NA",
    "EventLabel": "NewA|MB-MA-MA|mb1ma1maherschelss17|ALL|NA"
  },
  {
    "Placement": "mfb3",
    "Gender": "men",
    "Device": "desktop",
    "Image": "https://static-sg.zacdn.com/cms/DY/Mar2017/B1-6_322x165-espritmarch-men.jpg",
    "Exit Url": "/esprit-shop/?from=men",
    "Headline": "NA",
    "Subline": "NA",
    "EventLabel": "NewA|MC|esprit|ALL|NA"
  },
  {
    "Placement": "mfb4",
    "Gender": "men",
    "Device": "desktop",
    "Image": "https://static-sg.zacdn.com/cms/DY/Mar2017/B1-6_322x165-jackjonesmarch-men.jpg",
    "Exit Url": "/men/jack-jones/",
    "Headline": "NA",
    "Subline": "NA",
    "EventLabel": "NewA|MC|jackandjonesmar|ALL|NA"
  },
  {
    "Placement": "mfb5",
    "Gender": "men",
    "Device": "desktop",
    "Image": "https://static-sg.zacdn.com/cms/DY/Mar2017/B1-6_322x165-riverislandmarch-men.jpg",
    "Exit Url": "/river-island-singapore/?from=men",
    "Headline": "NA",
    "Subline": "NA",
    "EventLabel": "NewA|MC|riverislandmar|ALL|NA"
  },
  {
    "Placement": "mfb6",
    "Gender": "men",
    "Device": "desktop",
    "Image": "https://static-sg.zacdn.com/cms/DY/Mar2017/B1-6_322x165-cottononmarch-men.jpg",
    "Exit Url": "/cotton-on-shop/?from=men",
    "Headline": "NA",
    "Subline": "NA",
    "EventLabel": "NewA|MC|cottononmar|ALL|NA"
  },
  {
    "Placement": "mc1",
    "Gender": "men",
    "Device": "desktop",
    "Image": "https://static-sg.zacdn.com/cms/DY/Mar2017/C1245_300x198-shirtsmarch-men.jpg",
    "Exit Url": "/men/clothing/shirts/",
    "Headline": "NA",
    "Subline": "Shop Shirts >",
    "EventLabel": "SUB|MC|shirtsmen|ALL|NA"
  },
  {
    "Placement": "mc2",
    "Gender": "men",
    "Device": "desktop",
    "Image": "https://static-sg.zacdn.com/cms/DY/Mar2017/C1245_300x198-pantsmarch-men.jpg",
    "Exit Url": "/men/clothing/pants/",
    "Headline": "NA",
    "Subline": "Shop Pants >",
    "EventLabel": "SUB|MC|pantsmen|ALL|NA"
  },
  {
    "Placement": "mc3",
    "Gender": "men",
    "Device": "desktop",
    "Image": "https://static-sg.zacdn.com/cms/DY/Mar2017/C3_375x500-tshirtsmarch-men.jpg",
    "Exit Url": "/men/clothing/t-shirts/",
    "Headline": "NA",
    "Subline": "Shop T-Shirts >",
    "EventLabel": "SUB|MC|tshirtsmen|ALL|NA"
  },
  {
    "Placement": "mc4",
    "Gender": "men",
    "Device": "desktop",
    "Image": "https://static-sg.zacdn.com/cms/DY/Mar2017/C1245_300x198-sportsmarch-men.jpg",
    "Exit Url": "/men/sports/",
    "Headline": "NA",
    "Subline": "Shop Sports >",
    "EventLabel": "SUB|MSP|sportsmen|ALL|NA"
  },
  {
    "Placement": "mc5",
    "Gender": "men",
    "Device": "desktop",
    "Image": "https://static-sg.zacdn.com/cms/DY/Mar2017/C1245_300x198-backpacksmarch-men.jpg",
    "Exit Url": "/men/bags/backpacks/",
    "Headline": "NA",
    "Subline": "Shop Backpacks >",
    "EventLabel": "SUB|MB|backpacksmen|ALL|NA"
  },
  {
    "Placement": "wh1",
    "Gender": "women",
    "Device": "mobile",
    "Image": "https://static-sg.zacdn.com/cms/DY/Mar2017/MOBILEWEB_HERO_600x600-zaloraanniv-women.jpg",
    "Exit Url": "/women/zalora-anniversary/",
    "Headline": "NA",
    "Subline": "NA",
    "EventLabel": "TRE|NA|5thAnnivMar|ALL|NA|"
  },
  {
    "Placement": "wn1",
    "Gender": "women",
    "Device": "mobile",
    "Image": "https://static-sg.zacdn.com/cms/DY/Mar2017/N2_NEWARRIVALS_620x420-clarksmarch-women.jpg",
    "Exit Url": "/women/clarks",
    "Headline": "Women NCU1",
    "Subline": "Clarks",
    "EventLabel": "NewA|WS|wsclarksss17|ALL|NA|ZAP"
  },
  {
    "Placement": "wn2",
    "Gender": "women",
    "Device": "mobile",
    "Image": "https://static-sg.zacdn.com/cms/DY/Mar2017/N2_NEWARRIVALS_620x420-safari-women.jpg",
    "Exit Url": "/women/all-products/?cmpgn_one=safarianddesert",
    "Headline": "Women NCU2",
    "Subline": "Safari Traveller",
    "EventLabel": "TRE|Women|SafariTravellerandDesertMystic|ALL|NA"
  },
  {
    "Placement": "wc1",
    "Gender": "women",
    "Device": "mobile",
    "Image": "https://static-sg.zacdn.com/cms/DY/Mar2017/C1_300x198-topsmarch-women.jpg",
    "Exit Url": "",
    "Headline": "Women C1",
    "Subline": "Tops",
    "EventLabel": "SUB|WC|topsmarch|ALL|NA"
  },
  {
    "Placement": "wc2",
    "Gender": "women",
    "Device": "mobile",
    "Image": "https://static-sg.zacdn.com/cms/DY/Mar2017/C1_300x198-dressesmarch-women.jpg",
    "Exit Url": "/women/clothing/dresses/",
    "Headline": "Women C2",
    "Subline": "Dresses",
    "EventLabel": "SUB|WC|dressesswomen|ALL|NA"
  },
  {
    "Placement": "mh1",
    "Gender": "men",
    "Device": "mobile",
    "Image": "https://static-sg.zacdn.com/cms/DY/Mar2017/MOBILEWEB_HERO_600x600-zaloraanniv-men.jpg",
    "Exit Url": "/men/zalora-anniversary",
    "Headline": "NA",
    "Subline": "NA",
    "EventLabel": "TRE|Men|5thAnnivMar|ALL|NA"
  },
  {
    "Placement": "mn1",
    "Gender": "men",
    "Device": "mobile",
    "Image": "https://static-sg.zacdn.com/cms/DY/Mar2017/N2_NEWARRIVALS_620x420-shoesunder80-men.jpg",
    "Exit Url": "/men/all-products/?cmpgn_one=shoesforlessthan80&price=1-80",
    "Headline": "Men NCU1",
    "Subline": "Shoes Under $80",
    "EventLabel": "SAL|MS-|menshoesunder80|ALL|maxs|"
  },
  {
    "Placement": "mn2",
    "Gender": "men",
    "Device": "mobile",
    "Image": "https://static-sg.zacdn.com/cms/DY/Mar2017/N2_NEWARRIVALS_620x420-polostees17-men.jpg",
    "Exit Url": "/men/all-products/?cmpgn_one=polosandtees17",
    "Headline": "Men NCU2",
    "Subline": "Polos & Tees",
    "EventLabel": "CAT|MC|PolosandTeesMarch2017|ALL|NA|"
  },
  {
    "Placement": "mc1",
    "Gender": "men",
    "Device": "mobile",
    "Image": "https://static-sg.zacdn.com/cms/DY/Mar2017/C1245_300X198-shirts-men.jpg",
    "Exit Url": "/men/clothing/shirts/",
    "Headline": "Men C1",
    "Subline": "Shirts",
    "EventLabel": "SUB|MC|shirtsmen|ALL|NA"
  },
  {
    "Placement": "mc2",
    "Gender": "men",
    "Device": "mobile",
    "Image": "https://static-sg.zacdn.com/cms/DY/Mar2017/C1245_300x198-tshirtsmarch-men.jpg",
    "Exit Url": "/men/clothing/t-shirts/",
    "Headline": "Men C2",
    "Subline": "T-Shirts",
    "EventLabel": "SUB|MC|tshirtsmen|ALL|NA"
  },
  {
    "Placement": "uh1",
    "Gender": "unisex",
    "Device": "desktop",
    "Image": "https://static-sg.zacdn.com/cms/DY/Mar2017/HOMEPAGE_SPLASH_996x500-zaloraanniv.jpg",
    "Exit Url": "NA",
    "Headline": "NA",
    "Subline": "NA",
    "EventLabel": "THE|NA|homepagemain|ALL|NA"
  },
  {
    "Placement": "ub1",
    "Gender": "unisex",
    "Device": "desktop",
    "Image": "https://static-sg.zacdn.com/cms/fpseason/SEGMENT_HEADER_326x304-florals-hp-dsk.jpg",
    "Exit Url": "/women/all-products/floral/?getSKU=ST343AA42ITPMY",
    "Headline": "Blossoming Splendour",
    "Subline": "Floral prints to keep your wardrobe in bloom.",
    "EventLabel": "THE|NA|womenss17floralflowerstrend|ALL|NA"
  },
  {
    "Placement": "ub2",
    "Gender": "unisex",
    "Device": "desktop",
    "Image": "https://static-sg.zacdn.com/cms/Evergage/Feb2017/SEGMENT_HEADER_326x304-womenclothingna-unisex.jpg",
    "Exit Url": "/women/clothing/new-products/",
    "Headline": "New-In looks",
    "Subline": "Get a head start to new season trends. Discover the latest for Spring 2017.",
    "EventLabel": "THE|WC|newinlooksfeb|ALL|NA"
  },
  {
    "Placement": "ub3",
    "Gender": "unisex",
    "Device": "desktop",
    "Image": "https://static-sg.zacdn.com/cms/Evergage/Feb2017/SEGMENT_HEADER_326x304-menclothingna-unisex.jpg",
    "Exit Url": "/men/clothing/new-products/",
    "Headline": "Season Start",
    "Subline": "Our latest collection to update your look.",
    "EventLabel": "THE|MC|seasonstartfeb|ALL|NA"
  }
]