[
  {
    "Placement": "wh1",
    "Gender": "women",
    "Device": "desktop",
    "ENImageUrl": "https://static-hk.zacdn.com/cms/cw43/cw43_women_en_SEGMENT_HERO_996x500_CTA.jpg",
    "ZHImageUrl": "https://static-hk.zacdn.com/cms/cw43/cw43_women_zh_SEGMENT_HERO_996x500.jpg",
    "ExitUrl": "/women/new-products/?getSKU=DO816AA0RV35MY--BY867AA0RNOGMY--BY867AA0RNO8MY--RI009AA0RSDDMY--0EF62ZZ8E39FC8GS--NA323AA0RU82MY&csa=fallinloveoctobernewarrivals",
    "EventLabel": "TRE|Women|fallinloveoctobernewarrivals|ALL|NA",
    "ENHeadline": "NA",
    "ENSubline": "NA",
    "ZHHeadline": "NA",
    "ZHSubline": "NA"
  },
  {
    "Placement": "wn1",
    "Gender": "women",
    "Device": "desktop",
    "ENImageUrl": "https://static-hk.zacdn.com/cms/cw43/cw43_women_en_N1_NEWARRIVALS_360x420.jpg",
    "ZHImageUrl": "NA",
    "ExitUrl": "/women/levis-shop/?csa=levishk2awseventeen",
    "EventLabel": "bra|women|levishk2awseventeen|all|zap",
    "ENHeadline": "Levi's",
    "ENSubline": "Celebrate 50 years of the original denim jacket by getting one to call your own.",
    "ZHHeadline": "Levi's",
    "ZHSubline": "擁有專屬牛仔外套，慶祝品牌經典牛仔外套誕生50週年"
  },
  {
    "Placement": "wn2",
    "Gender": "women",
    "Device": "desktop",
    "ENImageUrl": "https://static-hk.zacdn.com/cms/cw43/cw43_women_en_zap_N2_NEWARRIVALS_620x420.jpg",
    "ZHImageUrl": "NA",
    "ExitUrl": "/calvin-klein-shop/?csa=calvinkleinawseventeen",
    "EventLabel": "bra|women|calvinkleinawseventeen|all|zap",
    "ENHeadline": "Calvin Klein",
    "ENSubline": "Put your best foot forward in clothing and accessories you can trust.",
    "ZHHeadline": "Calvin Klein",
    "ZHSubline": "選購優質品牌服飾，打造獨特穿搭風格"
  },
  {
    "Placement": "wn3",
    "Gender": "women",
    "Device": "desktop",
    "ENImageUrl": "https://static-hk.zacdn.com/cms/cw43/cw43_women_en_N3_HDILA_NEWARRIVALS_620x420.jpg",
    "ZHImageUrl": "NA",
    "ExitUrl": "/women/how-do-i-look-asia/?csa=HDILA7JewelTones",
    "EventLabel": "TRE|Women|HDILA7JewelTones|ALL|NA",
    "ENHeadline": "HOW DO I LOOK ASIA S3",
    "ENSubline": "See the jewel tones we're eyeing this season and own them right away.",
    "ZHHeadline": "HOW DO I LOOK ASIA S3",
    "ZHSubline": "立即收看影片，認識今季大熱寶石色系，盡收衣櫃"
  },
  {
    "Placement": "wn4",
    "Gender": "women",
    "Device": "desktop",
    "ENImageUrl": "https://static-hk.zacdn.com/cms/cw43/cw43_women_en__DesktopN4_NEWARRIVALS_360x420.jpg",
    "ZHImageUrl": "NA",
    "ExitUrl": "/women/feature/neutrals/?csa=nudeandneutrals",
    "EventLabel": "TRE|Women|nudeandneutrals|ALL|NA",
    "ENHeadline": "Nude and Neutrals Edit",
    "ENSubline": "Discover the colours and tones everyone’s been talking about.",
    "ZHHeadline": "裸色美感",
    "ZHSubline": "裸色系列襯托完美氣質"
  },
  {
    "Placement": "wcu1",
    "Gender": "women",
    "Device": "desktop",
    "ENImageUrl": "https://static-hk.zacdn.com/cms/cw25/N2_NEWARRIVALS_620x420-junebackinstock.jpg",
    "ZHImageUrl": "NA",
    "ExitUrl": "/women/all-products/?cmpgn_one=wsummervc18off&getSKU=RI009AA52NVRMY",
    "EventLabel": "NA|Women|BackInStock|ALL|NA",
    "ENHeadline": "Newly Restocked",
    "ENSubline": "Your second chance to get the clothes and shoes you’ve always wanted.",
    "ZHHeadline": "時尚單品再度入貨",
    "ZHSubline": "抓緊機會 別再錯過你喜愛的服飾及美鞋"
  },
  {
    "Placement": "wcu2",
    "Gender": "women",
    "Device": "desktop",
    "ENImageUrl": "https://static-hk.zacdn.com/cms/cw25/N1_NEWARRIVALS_360x420-shortsandtees.jpg",
    "ZHImageUrl": "NA",
    "ExitUrl": "/product-index/shortsandtees/",
    "EventLabel": "TRE|Women|ShortsAndTees|ALL|NA",
    "ENHeadline": "Laidback Staples",
    "ENSubline": "Beat the heat by pairing these must-have shorts and tees.",
    "ZHHeadline": "輕鬆慵懶時光",
    "ZHSubline": "百搭T恤短褲 休閒而不失時尚風格"
  },
  {
    "Placement": "wcu3",
    "Gender": "women",
    "Device": "desktop",
    "ENImageUrl": "https://static-hk.zacdn.com/cms/cw25/N1_NEWARRIVALS_360x420-maywevacay.jpg",
    "ZHImageUrl": "NA",
    "ExitUrl": "/women/clothing/tank-tops/",
    "EventLabel": "CAT|Women|CatPushSleevelssTops|ALL|NA",
    "ENHeadline": "Feel the Breeze",
    "ENSubline": "These sleeveless tops will give you the air of confidence you totally deserve.",
    "ZHHeadline": "清涼知性",
    "ZHSubline": "無袖上衣令造型清爽 帶出零負擔的穿搭自信"
  },
  {
    "Placement": "wcu4",
    "Gender": "women",
    "Device": "desktop",
    "ENImageUrl": "https://static-hk.zacdn.com/cms/cw25/CU2_CAMPAIGN_620x420-sportlounge.jpg",
    "ZHImageUrl": "NA",
    "ExitUrl": "/women/all-products/?cmpgn_one=sportlounge&getSKU=SU225AA81PRQMY--BY059AA99ZGYMY",
    "EventLabel": "TRE|Women|SportLounge|Women|NA",
    "ENHeadline": "The Lounge Life",
    "ENSubline": "Get cosy with relaxed tailoring and a touch of sports inspiration.",
    "ZHHeadline": "休閒生活態度",
    "ZHSubline": "柔軟舒適剪裁 伴你尋找運動樂趣"
  },
  {
    "Placement": "wfb1",
    "Gender": "women",
    "Device": "desktop",
    "ENImageUrl": "https://static-hk.zacdn.com/cms/cw43/cw43_women_B1_322x165.jpg",
    "ZHImageUrl": "NA",
    "ExitUrl": "/women/adidas/?csa=adidasoriginalsawseventeen",
    "EventLabel": "bra|women|adidasoriginalsawseventeen|all|na",
    "ENHeadline": "NA",
    "ENSubline": "NA",
    "ZHHeadline": "NA",
    "ZHSubline": "NA"
  },
  {
    "Placement": "wfb2",
    "Gender": "women",
    "Device": "desktop",
    "ENImageUrl": "https://static-hk.zacdn.com/cms/cw43/cw43_women_B2_322x165.jpg",
    "ZHImageUrl": "NA",
    "ExitUrl": "/women/oryany/?csa=oryanyawseventeen",
    "EventLabel": "bra|women|oryanyawseventeen|all|zap",
    "ENHeadline": "NA",
    "ENSubline": "NA",
    "ZHHeadline": "NA",
    "ZHSubline": "NA"
  },
  {
    "Placement": "wfb3",
    "Gender": "women",
    "Device": "desktop",
    "ENImageUrl": "https://static-hk.zacdn.com/cms/cw43/cw43_women_B3_322x165.jpg",
    "ZHImageUrl": "NA",
    "ExitUrl": "/miss-selfridge/?csa=missselfridgeawseventeen",
    "EventLabel": "bra|women|missselfridgeawseventeen|all|na",
    "ENHeadline": "NA",
    "ENSubline": "NA",
    "ZHHeadline": "NA",
    "ZHSubline": "NA"
  },
  {
    "Placement": "wfb4",
    "Gender": "women",
    "Device": "desktop",
    "ENImageUrl": "https://static-hk.zacdn.com/cms/cw43/cw43_women_B4_322x165.jpg",
    "ZHImageUrl": "NA",
    "ExitUrl": "/women/something-borrowed/?csa=somethingborrowed",
    "EventLabel": "BRA|Women|somethingborrowed|ALL|NA",
    "ENHeadline": "NA",
    "ENSubline": "NA",
    "ZHHeadline": "NA",
    "ZHSubline": "NA"
  },
  {
    "Placement": "wfb5",
    "Gender": "women",
    "Device": "desktop",
    "ENImageUrl": "https://static-hk.zacdn.com/cms/cw43/cw43_women_B5_322x165.jpg",
    "ZHImageUrl": "NA",
    "ExitUrl": "/women/goddiva/?csa=goddivaawseventeen",
    "EventLabel": "BRA|Women|goddivaawseventeen|ALL|NA",
    "ENHeadline": "NA",
    "ENSubline": "NA",
    "ZHHeadline": "NA",
    "ZHSubline": "NA"
  },
  {
    "Placement": "wfb6",
    "Gender": "women",
    "Device": "desktop",
    "ENImageUrl": "https://static-hk.zacdn.com/cms/cw43/cw43_women_B6_322x165.jpg",
    "ZHImageUrl": "NA",
    "ExitUrl": "/women/call-it-spring/?csa=callitspringawseventeen",
    "EventLabel": "BRA|Women|callitspringawseventeen|ALL|NA",
    "ENHeadline": "NA",
    "ENSubline": "NA",
    "ZHHeadline": "NA",
    "ZHSubline": "NA"
  },
  {
    "Placement": "wc1",
    "Gender": "women",
    "Device": "desktop",
    "ENImageUrl": "https://static-hk.zacdn.com/cms/cw43/cw43_C1_300x198_TOPS.jpg",
    "ZHImageUrl": "NA",
    "ExitUrl": "/women/clothing/fashion-tops/?csa=tops",
    "EventLabel": "CAT|Women|tops|ALL|NA",
    "ENHeadline": "NA",
    "ENSubline": "SHOP TOPS>",
    "ZHHeadline": "NA",
    "ZHSubline": "選購上衣>"
  },
  {
    "Placement": "wc2",
    "Gender": "women",
    "Device": "desktop",
    "ENImageUrl": "https://static-hk.zacdn.com/cms/cw43/cw43_C2_300x198_SKIRTS.jpg",
    "ZHImageUrl": "NA",
    "ExitUrl": "/women/clothing/skirts/?csa=skirts",
    "EventLabel": "CAT|Women|skirts|ALL|NA",
    "ENHeadline": "NA",
    "ENSubline": "SHOP SKIRTS>",
    "ZHHeadline": "NA",
    "ZHSubline": "選購半截裙>"
  },
  {
    "Placement": "wc3",
    "Gender": "women",
    "Device": "desktop",
    "ENImageUrl": "https://static-hk.zacdn.com/cms/cw43/cw43_C3_375x500_DRESSES.jpg",
    "ZHImageUrl": "NA",
    "ExitUrl": "/women/clothing/dresses/?csa=dresses",
    "EventLabel": "CAT|Women|dresses|ALL|NA",
    "ENHeadline": "NA",
    "ENSubline": "SHOP DRESSES>",
    "ZHHeadline": "NA",
    "ZHSubline": "選購連身裙>"
  },
  {
    "Placement": "wc4",
    "Gender": "women",
    "Device": "desktop",
    "ENImageUrl": "https://static-hk.zacdn.com/cms/cw43/cw43_C4_300x198_HEELS.jpg",
    "ZHImageUrl": "NA",
    "ExitUrl": "/women/shoes/heels/?csa=heels",
    "EventLabel": "CAT|Women|heels|ALL|NA",
    "ENHeadline": "NA",
    "ENSubline": "SHOP HEELS>",
    "ZHHeadline": "NA",
    "ZHSubline": "選購高跟鞋>"
  },
  {
    "Placement": "wc5",
    "Gender": "women",
    "Device": "desktop",
    "ENImageUrl": "https://static-hk.zacdn.com/cms/cw43/cw43_C5_300x198_ACCESSORIES.jpg",
    "ZHImageUrl": "NA",
    "ExitUrl": "/women/accessories/?csa=accessories",
    "EventLabel": "CAT|Women|accessories|ALL|NA",
    "ENHeadline": "NA",
    "ENSubline": "SHOP ACCESSORIES>",
    "ZHHeadline": "NA",
    "ZHSubline": "選購飾物>"
  },
  {
    "Placement": "mh1",
    "Gender": "men",
    "Device": "desktop",
    "ENImageUrl": "https://static-hk.zacdn.com/cms/cw43/cw43_men_en_SEGMENT_HERO_MOCKUP_996x500.jpg",
    "ZHImageUrl": "https://static-hk.zacdn.com/cms/cw43/cw43_men_zh_SEGMENT_HERO_MOCKUP_996x500.jpg",
    "ExitUrl": "/men/all-products/?age=0-30&csa=octnewarrivals",
    "EventLabel": "TRE|Men|octnewarrivals|ALL|NA",
    "ENHeadline": "NA",
    "ENSubline": "NA",
    "ZHHeadline": "NA",
    "ZHSubline": "NA"
  },
  {
    "Placement": "mn1",
    "Gender": "men",
    "Device": "desktop",
    "ENImageUrl": "https://static-hk.zacdn.com/cms/cw43/cw43_men_en_zap_N1_NEWARRIVALS_360x420.jpg",
    "ZHImageUrl": "NA",
    "ExitUrl": "/men/levis-shop/?csa=levishk2awseventeen",
    "EventLabel": "bra|men|levishk2awseventeen|all|zap",
    "ENHeadline": "Levi's",
    "ENSubline": "Celebrate 50 years of the original denim jacket by getting one to call your own.",
    "ZHHeadline": "Levi's",
    "ZHSubline": "擁有專屬牛仔外套，慶祝品牌經典牛仔外套誕生50週年"
  },
  {
    "Placement": "mn2",
    "Gender": "men",
    "Device": "desktop",
    "ENImageUrl": "https://static-hk.zacdn.com/cms/cw43/cw43_men_zap_N2_NEWARRIVALS_620x420.jpg",
    "ZHImageUrl": "NA",
    "ExitUrl": "/calvin-klein-shop/?csa=calvinkleinawseventeen",
    "EventLabel": "bra|men|calvinkleinawseventeen|all|zap",
    "ENHeadline": "Calvin Klein",
    "ENSubline": "Put your best foot forward in clothing and accessories you can trust.",
    "ZHHeadline": "Calvin Klein",
    "ZHSubline": "選購優質品牌服飾，打造獨特穿搭風格"
  },
  {
    "Placement": "mn3",
    "Gender": "men",
    "Device": "desktop",
    "ENImageUrl": "https://static-hk.zacdn.com/cms/cw43/cw43_men_en_N3_NEWARRIVALS_620x420.jpg",
    "ZHImageUrl": "NA",
    "ExitUrl": "/men/all-products/?cmpgn_one=bohoman&csa=bohoman",
    "EventLabel": "TRE|Men|bohoman|ALL|NA",
    "ENHeadline": "Effortlessly Boho",
    "ENSubline": "Forget everything you knew about typical styling and dress down in total comfort.",
    "ZHHeadline": "不羈風格",
    "ZHSubline": "拋開平日風格，嘗試休閒舒適造型"
  },
  {
    "Placement": "mn4",
    "Gender": "men",
    "Device": "desktop",
    "ENImageUrl": "https://static-hk.zacdn.com/cms/cw43/cw43_men_en_N4_NEWARRIVALS_360x420.jpg",
    "ZHImageUrl": "NA",
    "ExitUrl": "/men/all-products/special-price/?discount=0-60&csa=lastofmss",
    "EventLabel": "SAL|Men|lastofmss|ALL|NA",
    "ENHeadline": "Final Call - Up to 60% Off",
    "ENSubline": "Sale’s about to be over, so don’t let this limited time offer slip away.",
    "ZHHeadline": "最後召集 - 低至4折",
    "ZHSubline": "把握最後機會，低價擁有心頭好"
  },
  {
    "Placement": "mfb1",
    "Gender": "men",
    "Device": "desktop",
    "ENImageUrl": "https://static-hk.zacdn.com/cms/cw43/cw43_men_B1_322x165.jpg",
    "ZHImageUrl": "NA",
    "ExitUrl": "/men/adidas-shop/?csa=AdidasHKLaunchssseventeen",
    "EventLabel": "BRA|Men|AdidasHKLaunchssseventeen|ALL|NA",
    "ENHeadline": "NA",
    "ENSubline": "NA",
    "ZHHeadline": "NA",
    "ZHSubline": "NA"
  },
  {
    "Placement": "mfb2",
    "Gender": "men",
    "Device": "desktop",
    "ENImageUrl": "https://static-hk.zacdn.com/cms/cw43/cw43_men_B2_322x165.jpg",
    "ZHImageUrl": "NA",
    "ExitUrl": "/men/invicta/?csa=invictaawseventeen",
    "EventLabel": "BRA|Men|invictaawseventeen|ALL|ZAP",
    "ENHeadline": "NA",
    "ENSubline": "NA",
    "ZHHeadline": "NA",
    "ZHSubline": "NA"
  },
  {
    "Placement": "mfb3",
    "Gender": "men",
    "Device": "desktop",
    "ENImageUrl": "https://static-hk.zacdn.com/cms/cw43/cw43_men_B3_322x165.jpg",
    "ZHImageUrl": "NA",
    "ExitUrl": "/men/oakley/?csa=oakleyawseventeen",
    "EventLabel": "bra|men|oakleyawseventeen|all|na",
    "ENHeadline": "NA",
    "ENSubline": "NA",
    "ZHHeadline": "NA",
    "ZHSubline": "NA"
  },
  {
    "Placement": "mfb4",
    "Gender": "men",
    "Device": "desktop",
    "ENImageUrl": "https://static-hk.zacdn.com/cms/cw43/cw43_men_B4_322x165_converse.jpg",
    "ZHImageUrl": "NA",
    "ExitUrl": "/men/converse/?csa=conversamss",
    "EventLabel": "SAL|MS|conversamss|ALL|maxp",
    "ENHeadline": "NA",
    "ENSubline": "NA",
    "ZHHeadline": "NA",
    "ZHSubline": "NA"
  },
  {
    "Placement": "mfb5",
    "Gender": "men",
    "Device": "desktop",
    "ENImageUrl": "https://static-hk.zacdn.com/cms/cw43/cw43_men_B5_322x165.jpg",
    "ZHImageUrl": "NA",
    "ExitUrl": "/men/hollister/?csa=hollisterawseventeen",
    "EventLabel": "BRA|Men|hollisterawseventeen|ALL|NA",
    "ENHeadline": "NA",
    "ENSubline": "NA",
    "ZHHeadline": "NA",
    "ZHSubline": "NA"
  },
  {
    "Placement": "mfb6",
    "Gender": "men",
    "Device": "desktop",
    "ENImageUrl": "https://static-hk.zacdn.com/cms/cw43/cw43_men_B6_322x165.jpg",
    "ZHImageUrl": "NA",
    "ExitUrl": "/men/mango-shop/?csa=mangoawseventeen",
    "EventLabel": "BRA|Men|mangoawseventeen|ALL|NA",
    "ENHeadline": "NA",
    "ENSubline": "NA",
    "ZHHeadline": "NA",
    "ZHSubline": "NA"
  },
  {
    "Placement": "mc1",
    "Gender": "men",
    "Device": "desktop",
    "ENImageUrl": "https://static-hk.zacdn.com/cms/cw43/cw43_men_C1_300x198_Shorts.jpg",
    "ZHImageUrl": "NA",
    "ExitUrl": "/men/clothing/pants/?csa=pants",
    "EventLabel": "CAT|Men|pants|ALL|NA",
    "ENHeadline": "NA",
    "ENSubline": "SHOP PANTS>",
    "ZHHeadline": "NA",
    "ZHSubline": "選購長褲>"
  },
  {
    "Placement": "mc2",
    "Gender": "men",
    "Device": "desktop",
    "ENImageUrl": "https://static-hk.zacdn.com/cms/cw43/cw43_men_C2_300x198_FormalShoes.jpg",
    "ZHImageUrl": "NA",
    "ExitUrl": "/men/shoes/formal-shoes/?csa=businessshoes",
    "EventLabel": "CAT|Men|businessshoes|ALL|NA",
    "ENHeadline": "NA",
    "ENSubline": "SHOP BUSINESS SHOES>",
    "ZHHeadline": "NA",
    "ZHSubline": "選購 正式鞋>"
  },
  {
    "Placement": "mc3",
    "Gender": "men",
    "Device": "desktop",
    "ENImageUrl": "https://static-hk.zacdn.com/cms/cw43/cw43_men_C3_375x500_Tshirts.jpg",
    "ZHImageUrl": "NA",
    "ExitUrl": "/men/clothing/t-shirts/?csa=tshirts",
    "EventLabel": "CAT|Men|tshirts|ALL|NA",
    "ENHeadline": "NA",
    "ENSubline": "SHOP TSHIRTS>",
    "ZHHeadline": "NA",
    "ZHSubline": "選購T恤>"
  },
  {
    "Placement": "mc4",
    "Gender": "men",
    "Device": "desktop",
    "ENImageUrl": "https://static-hk.zacdn.com/cms/cw43/cw43_men_C4_300x198_sweatshirts.jpg",
    "ZHImageUrl": "NA",
    "ExitUrl": "/men/clothing/hoodies-sweatshirts/?csa=hoodiesandsweatshirts",
    "EventLabel": "CAT|Men|hoodiesandsweatshirts|ALL|NA",
    "ENHeadline": "NA",
    "ENSubline": "SHOP HOODIES & SWEATSHIRTS>",
    "ZHHeadline": "NA",
    "ZHSubline": "選購衛衣低>"
  },
  {
    "Placement": "mc5",
    "Gender": "men",
    "Device": "desktop",
    "ENImageUrl": "https://static-hk.zacdn.com/cms/cw43/cw43_men_C5_300x198_WATCHES.jpg",
    "ZHImageUrl": "NA",
    "ExitUrl": "/men/watches/?csa=watches",
    "EventLabel": "CAT|Men|watches|ALL|NA",
    "ENHeadline": "NA",
    "ENSubline": "SHOP WATCHES>",
    "ZHHeadline": "NA",
    "ZHSubline": "選購手錶>"
  },
  {
    "Placement": "wh1",
    "Gender": "women",
    "Device": "mobile",
    "ENImageUrl": "https://static-hk.zacdn.com/cms/cw43/cw43_women_en_MOBILEWEB_HERO_600x600.jpg",
    "ZHImageUrl": "https://static-hk.zacdn.com/cms/cw43/cw43_women_zh_MOBILEWEB_HERO_600x600.jpg",
    "ExitUrl": "/women/new-products/?getSKU=DO816AA0RV35MY--BY867AA0RNOGMY--BY867AA0RNO8MY--RI009AA0RSDDMY--0EF62ZZ8E39FC8GS--NA323AA0RU82MY&csa=fallinloveoctobernewarrivals",
    "EventLabel": "TRE|Women|fallinloveoctobernewarrivals|ALL|NA",
    "ENHeadline": "NA",
    "ENSubline": "NA",
    "ZHHeadline": "NA",
    "ZHSubline": "NA"
  },
  {
    "Placement": "wn1",
    "Gender": "women",
    "Device": "mobile",
    "ENImageUrl": "https://static-hk.zacdn.com/cms/cw43/cw43_women_en_N1mob_NEWARRIVALS_620x420.jpg",
    "ZHImageUrl": "NA",
    "ExitUrl": "/levis-shop/?csa=levishk2awseventeen",
    "EventLabel": "bra|women|levishk2awseventeen|all|zap",
    "ENHeadline": "Levi's",
    "ENSubline": "Celebrate 50 years of the original denim jacket by getting one to call your own.",
    "ZHHeadline": "Levi's",
    "ZHSubline": "擁有專屬牛仔外套，慶祝品牌經典牛仔外套誕生50週年"
  },
  {
    "Placement": "wn2",
    "Gender": "women",
    "Device": "mobile",
    "ENImageUrl": "https://static-hk.zacdn.com/cms/cw43/cw43_women_en_zap_N2_NEWARRIVALS_620x420.jpg",
    "ZHImageUrl": "NA",
    "ExitUrl": "/calvin-klein-shop/?csa=calvinkleinawseventeen",
    "EventLabel": "bra|women|calvinkleinawseventeen|all|zap",
    "ENHeadline": "Calvin Klein",
    "ENSubline": "Put your best foot forward in clothing and accessories you can trust.",
    "ZHHeadline": "Calvin Klein",
    "ZHSubline": "選購優質品牌服飾，打造獨特穿搭風格"
  },
  {
    "Placement": "wn3",
    "Gender": "women",
    "Device": "mobile",
    "ENImageUrl": "https://static-hk.zacdn.com/cms/cw43/cw43_women_en_N3_HDILA_NEWARRIVALS_620x420.jpg",
    "ZHImageUrl": "NA",
    "ExitUrl": "/women/how-do-i-look-asia/?csa=HDILA7JewelTones",
    "EventLabel": "TRE|Women|HDILA7JewelTones|ALL|NA",
    "ENHeadline": "HOW DO I LOOK ASIA S3",
    "ENSubline": "See the jewel tones we're eyeing this season and own them right away.",
    "ZHHeadline": "HOW DO I LOOK ASIA S3",
    "ZHSubline": "立即收看影片，認識今季大熱寶石色系，盡收衣櫃"
  },
  {
    "Placement": "wc1",
    "Gender": "women",
    "Device": "mobile",
    "ENImageUrl": "https://static-hk.zacdn.com/cms/cw43/cw43_C1_300x198_TOPS.jpg",
    "ZHImageUrl": "NA",
    "ExitUrl": "/women/clothing/fashion-tops/?csa=tops",
    "EventLabel": "CAT|Women|tops|ALL|NA",
    "ENHeadline": "SHOP TOPS>",
    "ENSubline": "SHOP TOPS>",
    "ZHHeadline": "選購上衣>",
    "ZHSubline": "選購上衣>"
  },
  {
    "Placement": "wc2",
    "Gender": "women",
    "Device": "mobile",
    "ENImageUrl": "https://static-hk.zacdn.com/cms/cw43/cw43_C3mob_300x198_DRESSES.jpg",
    "ZHImageUrl": "NA",
    "ExitUrl": "/women/clothing/dresses/?csa=dresses",
    "EventLabel": "CAT|Women|dresses|ALL|NA",
    "ENHeadline": "SHOP DRESSES>",
    "ENSubline": "SHOP DRESSES>",
    "ZHHeadline": "選購連身裙>",
    "ZHSubline": "選購連身裙>"
  },
  {
    "Placement": "mh1",
    "Gender": "men",
    "Device": "mobile",
    "ENImageUrl": "https://static-hk.zacdn.com/cms/cw43/cw43_men_en_mobile_Hero_600x600.jpg",
    "ZHImageUrl": "https://static-hk.zacdn.com/cms/cw43/cw43_men_zh_mobile_hero_600x600.jpg",
    "ExitUrl": "/men/all-products/?age=0-30&csa=octnewarrivals",
    "EventLabel": "TRE|Men|octnewarrivals|ALL|NA",
    "ENHeadline": "NA",
    "ENSubline": "NA",
    "ZHHeadline": "NA",
    "ZHSubline": "NA"
  },
  {
    "Placement": "mn1",
    "Gender": "men",
    "Device": "mobile",
    "ENImageUrl": "https://static-hk.zacdn.com/cms/cw43/cw43_men_en_zap_N1mob_NEWARRIVALS_620x420.jpg",
    "ZHImageUrl": "NA",
    "ExitUrl": "/men/levis/?csa=levishk2awseventeen",
    "EventLabel": "bra|men|levishk2awseventeen|all|zap",
    "ENHeadline": "Levi's",
    "ENSubline": "Celebrate 50 years of the original denim jacket by getting one to call your own.",
    "ZHHeadline": "Levi's",
    "ZHSubline": "擁有專屬牛仔外套，慶祝品牌經典牛仔外套誕生50週年"
  },
  {
    "Placement": "mn2",
    "Gender": "men",
    "Device": "mobile",
    "ENImageUrl": "https://static-hk.zacdn.com/cms/cw43/cw43_men_zap_N2_NEWARRIVALS_620x420.jpg",
    "ZHImageUrl": "NA",
    "ExitUrl": "/calvin-klein-shop/?csa=calvinkleinawseventeen",
    "EventLabel": "bra|men|calvinkleinawseventeen|all|zap",
    "ENHeadline": "Calvin Klein",
    "ENSubline": "Put your best foot forward in clothing and accessories you can trust.",
    "ZHHeadline": "Calvin Klein",
    "ZHSubline": "選購優質品牌服飾，打造獨特穿搭風格"
  },
  {
    "Placement": "mn3",
    "Gender": "men",
    "Device": "mobile",
    "ENImageUrl": "https://static-hk.zacdn.com/cms/cw43/cw43_men_en_N3_NEWARRIVALS_620x420.jpg",
    "ZHImageUrl": "NA",
    "ExitUrl": "/men/all-products/?cmpgn_one=bohoman&csa=bohoman",
    "EventLabel": "TRE|Men|bohoman|ALL|NA",
    "ENHeadline": "Effortlessly Boho",
    "ENSubline": "Forget everything you knew about typical styling and dress down in total comfort.",
    "ZHHeadline": "不羈風格",
    "ZHSubline": "拋開平日風格，嘗試休閒舒適造型"
  },
  {
    "Placement": "mc1",
    "Gender": "men",
    "Device": "mobile",
    "ENImageUrl": "https://static-hk.zacdn.com/cms/cw43/cw43_men_C1_300x198_Shorts.jpg",
    "ZHImageUrl": "NA",
    "ExitUrl": "/men/clothing/pants/?csa=pants",
    "EventLabel": "CAT|Men|pants|ALL|NA",
    "ENHeadline": "SHOP PANTS>",
    "ENSubline": "SHOP PANTS>",
    "ZHHeadline": "選購長褲>",
    "ZHSubline": "選購長褲>"
  },
  {
    "Placement": "mc2",
    "Gender": "men",
    "Device": "mobile",
    "ENImageUrl": "https://static-hk.zacdn.com/cms/cw43/cw43_men_C3mob_300x198_Tshirts.jpg",
    "ZHImageUrl": "NA",
    "ExitUrl": "/men/clothing/t-shirts/?csa=tshirts",
    "EventLabel": "CAT|Men|tshirts|ALL|NA",
    "ENHeadline": "SHOP TSHIRTS>",
    "ENSubline": "SHOP TSHIRTS>",
    "ZHHeadline": "選購T恤>",
    "ZHSubline": "選購T恤>"
  },
  {
    "Placement": "uh1",
    "Gender": "unisex",
    "Device": "desktop",
    "ENImageUrl": "https://static-hk.zacdn.com/cms/cw32/HOMEPAGE_SPLASH_unisex_996x500.jpg",
    "ZHImageUrl": "https://static-hk.zacdn.com/cms/cw32/HOMEPAGE_SPLASH_unisex_996x500.jpg",
    "ExitUrl": "NA",
    "EventLabel": "NA",
    "ENHeadline": "NA",
    "ENSubline": "NA",
    "ZHHeadline": "NA",
    "ZHSubline": "NA"
  },
  {
    "Placement": "ub1",
    "Gender": "unisex",
    "Device": "desktop",
    "ENImageUrl": "https://static-hk.zacdn.com/cms/cw42/cw42_women_en_N4_HOMEPAGE_BOTTOMBANNER_326x304.jpg",
    "ZHImageUrl": "NA",
    "ExitUrl": "/women/all-products/?brand=casio--vans--ray-ban--melissa--mango--dorothy-perkins--topshop--miss-selfridge--river-island--cotton-on--cotton-on-body--missguided--factorie--eyescream--esprit&discount=20-60&csa=bestbrandssixtyoff",
    "EventLabel": "SAL|Women|bestbrandssixtyoff|ALL|NA",
    "ENHeadline": "Top Brands Up to 60% Off",
    "ENSubline": "Why settle for less when you can get your hands on the very best?",
    "ZHHeadline": "熱門品牌低至4折",
    "ZHSubline": "當你值得最好時，為何仍要退而求其次?"
  },
  {
    "Placement": "ub2",
    "Gender": "unisex",
    "Device": "desktop",
    "ENImageUrl": "https://static-hk.zacdn.com/cms/cw42/cw41_women_UB2_SEGMENT_HEADER_326x304.jpg",
    "ZHImageUrl": "NA",
    "ExitUrl": "/women/all-products/?cmpgn_one=twotwentythreethirty&csa=twotwentythreethirty",
    "EventLabel": "SAL|Women|twotwentythreethirty|ALL|NA",
    "ENHeadline": "Buy 2 Get 20% Off <brr> Buy 3 Or More Get 30% Off",
    "ENSubline": "Your fashion haul just got bigger and better.",
    "ZHHeadline": "買2件8折<br>買3件或以上7折",
    "ZHSubline": "更多更好的衣飾，讓你更期待開箱"
  },
  {
    "Placement": "ub3",
    "Gender": "unisex",
    "Device": "desktop",
    "ENImageUrl": "https://static-hk.zacdn.com/cms/cw42/cw42_men_en_N3_SEGMENT_HEADER_326x304.jpg",
    "ZHImageUrl": "NA",
    "ExitUrl": "/men/all-products/?brand=life8--burton-menswear-london--converse--cotton-on--factorie--fjallraven-kanken--hollister--jack-jones--jaxon--mango-man--river-island&discount=20-40&csa=highstreetthirty",
    "EventLabel": "SAL|Men|highstreetthirty|ALL|NA",
    "ENHeadline": "Premium Picks Up to 40% Off",
    "ENSubline": "Let these high street threads tell the story of your unspoken style.",
    "ZHHeadline": "高街品牌低至6折",
    "ZHSubline": "讓高街服飾展現你的低調時尚風格"
  },
  {
    "Placement": "wb1",
    "Gender": "women",
    "Device": "mobile",
    "ENImageUrl": "https://static-hk.zacdn.com/cms/cw28/Logo_436x248-vacae.jpg",
    "ZHImageUrl": "NA",
    "ExitUrl": "/women/vacae/",
    "EventLabel": "BRA|Women|vacaessseventeen|ALL|ZAP",
    "ENHeadline": "NA",
    "ENSubline": "NA",
    "ZHHeadline": "NA",
    "ZHSubline": "NA"
  },
  {
    "Placement": "wb2",
    "Gender": "women",
    "Device": "mobile",
    "ENImageUrl": "https://static-hk.zacdn.com/cms/marchmss2017/mobile_brand_logo_436x248-somethingborrowed.gif",
    "ZHImageUrl": "NA",
    "ExitUrl": "/women/something-borrowed/",
    "EventLabel": "SAL|MC|somethingborrowed|ALL|maxp",
    "ENHeadline": "NA",
    "ENSubline": "NA",
    "ZHHeadline": "NA",
    "ZHSubline": "NA"
  },
  {
    "Placement": "wb3",
    "Gender": "women",
    "Device": "mobile",
    "ENImageUrl": "https://static-hk.zacdn.com/cms/marchmss2017/mobile_brand_logo_436x248-rubi.gif",
    "ZHImageUrl": "NA",
    "ExitUrl": "/women/rubi/",
    "EventLabel": "SAL|MC|rubi|ALL|maxp",
    "ENHeadline": "NA",
    "ENSubline": "NA",
    "ZHHeadline": "NA",
    "ZHSubline": "NA"
  },
  {
    "Placement": "wb4",
    "Gender": "women",
    "Device": "mobile",
    "ENImageUrl": "https://static-hk.zacdn.com/cms/marchmss2017/mobile_brand_logo_436x248-betsy.gif",
    "ZHImageUrl": "NA",
    "ExitUrl": "/women/betsy/",
    "EventLabel": "SAL|MC|betsy|ALL|maxp",
    "ENHeadline": "NA",
    "ENSubline": "NA",
    "ZHHeadline": "NA",
    "ZHSubline": "NA"
  },
  {
    "Placement": "mb1",
    "Gender": "men",
    "Device": "mobile",
    "ENImageUrl": "https://static-hk.zacdn.com/cms/Evergage/mobile_brands_zalora.gif",
    "ZHImageUrl": "NA",
    "ExitUrl": "/men/zalora/",
    "EventLabel": "BRA|MC|zalora|ALL|NA",
    "ENHeadline": "NA",
    "ENSubline": "NA",
    "ZHHeadline": "NA",
    "ZHSubline": "NA"
  },
  {
    "Placement": "mb2",
    "Gender": "men",
    "Device": "mobile",
    "ENImageUrl": "https://static-hk.zacdn.com/cms/Evergage/Swan/mobile_brands_mangoman.gif",
    "ZHImageUrl": "NA",
    "ExitUrl": "/men/mango-man/",
    "EventLabel": "BRA|MC|mangoman|ALL|NA",
    "ENHeadline": "NA",
    "ENSubline": "NA",
    "ZHHeadline": "NA",
    "ZHSubline": "NA"
  },
  {
    "Placement": "mb3",
    "Gender": "men",
    "Device": "mobile",
    "ENImageUrl": "https://static-hk.zacdn.com/cms/Evergage/Swan/mobile_brands_superdry.gif",
    "ZHImageUrl": "NA",
    "ExitUrl": "/men/superdry/",
    "EventLabel": "BRA|MC|superdry|ALL|NA",
    "ENHeadline": "NA",
    "ENSubline": "NA",
    "ZHHeadline": "NA",
    "ZHSubline": "NA"
  },
  {
    "Placement": "mb4",
    "Gender": "men",
    "Device": "mobile",
    "ENImageUrl": "https://static-hk.zacdn.com/cms/Evergage/Swan/mobile_brands_aldo.gif",
    "ZHImageUrl": "NA",
    "ExitUrl": "/men/aldo/",
    "EventLabel": "BRA|MC|aldo|ALL|NA",
    "ENHeadline": "NA",
    "ENSubline": "NA",
    "ZHHeadline": "NA",
    "ZHSubline": "NA"
  },
  {
    "Placement": "skinny-full-homepage",
    "Gender": "unisex",
    "Device": "desktop",
    "ENImageUrl": "url('https://static-hk.zacdn.com/cms/cw27/SKINNY_SLICED_996x25-womens.jpg')",
    "ZHImageUrl": "/beta-erv/",
    "ExitUrl": "Lorem ipsum blahblahblah",
    "EventLabel": "#FFF",
    "ENHeadline": "SAL|NA|skinnyfullcampaign|ALL|NA",
    "ENSubline": "",
    "ZHHeadline": "",
    "ZHSubline": ""
  },
  {
    "Placement": "skinny-half-left-homepage",
    "Gender": "unisex",
    "Device": "desktop",
    "ENImageUrl": "url('https://static-hk.zacdn.com/cms/cw27/SKINNY_SLICED_996x25-womens.jpg')",
    "ZHImageUrl": "/beta-erv/",
    "ExitUrl": "Lorem ipsum blahblahblah",
    "EventLabel": "#FFF",
    "ENHeadline": "SAL|NA|skinnyhalfleftcampaign|ALL|NA",
    "ENSubline": "",
    "ZHHeadline": "",
    "ZHSubline": ""
  },
  {
    "Placement": "skinny-half-right-homepage",
    "Gender": "unisex",
    "Device": "desktop",
    "ENImageUrl": "url('https://static-hk.zacdn.com/cms/cw27/SKINNY_SLICED_996x25-womens.jpg')",
    "ZHImageUrl": "/beta-erv/",
    "ExitUrl": "Lorem ipsum blahblahblah",
    "EventLabel": "#FFF",
    "ENHeadline": "SAL|NA|skinnyhalfrightcampaign|ALL|NA",
    "ENSubline": "",
    "ZHHeadline": "",
    "ZHSubline": ""
  },
  {
    "Placement": "skinny-full-women",
    "Gender": "women",
    "Device": "desktop",
    "ENImageUrl": "url('https://static-hk.zacdn.com/cms/cw27/SKINNY_SLICED_996x25-womens.jpg')",
    "ZHImageUrl": "/beta-erv/",
    "ExitUrl": "Lorem ipsum blahblahblah",
    "EventLabel": "#FFF",
    "ENHeadline": "SAL|Women|skinnyfullcampaign|ALL|NA",
    "ENSubline": "",
    "ZHHeadline": "",
    "ZHSubline": ""
  },
  {
    "Placement": "skinny-half-left-women",
    "Gender": "women",
    "Device": "desktop",
    "ENImageUrl": "url('https://static-hk.zacdn.com/cms/cw27/SKINNY_SLICED_996x25-womens.jpg')",
    "ZHImageUrl": "/beta-erv/",
    "ExitUrl": "Lorem ipsum blahblahblah",
    "EventLabel": "#FFF",
    "ENHeadline": "SAL|Women|skinnyhalfleftcampaign|ALL|NA",
    "ENSubline": "",
    "ZHHeadline": "",
    "ZHSubline": ""
  },
  {
    "Placement": "skinny-half-right-women",
    "Gender": "women",
    "Device": "desktop",
    "ENImageUrl": "url('https://static-hk.zacdn.com/cms/cw27/SKINNY_SLICED_996x25-womens.jpg')",
    "ZHImageUrl": "/beta-erv/",
    "ExitUrl": "Lorem ipsum blahblahblah",
    "EventLabel": "#FFF",
    "ENHeadline": "SAL|Women|skinnyhalfrightcampaign|ALL|NA",
    "ENSubline": "",
    "ZHHeadline": "",
    "ZHSubline": ""
  },
  {
    "Placement": "skinny-full-men",
    "Gender": "men",
    "Device": "desktop",
    "ENImageUrl": "#000",
    "ZHImageUrl": "/beta-erv/",
    "ExitUrl": "Lorem ipsum blahblahblah",
    "EventLabel": "#FFF",
    "ENHeadline": "SAL|Men|skinnyfullcampaign|ALL|NA",
    "ENSubline": "",
    "ZHHeadline": "",
    "ZHSubline": ""
  },
  {
    "Placement": "skinny-half-left-men",
    "Gender": "men",
    "Device": "desktop",
    "ENImageUrl": "#000",
    "ZHImageUrl": "/beta-erv/",
    "ExitUrl": "Lorem ipsum blahblahblah",
    "EventLabel": "#FFF",
    "ENHeadline": "SAL|Men|skinnyhalfleftcampaign|ALL|NA",
    "ENSubline": "",
    "ZHHeadline": "",
    "ZHSubline": ""
  },
  {
    "Placement": "skinny-half-right-men",
    "Gender": "men",
    "Device": "desktop",
    "ENImageUrl": "#000",
    "ZHImageUrl": "/beta-erv/",
    "ExitUrl": "Lorem ipsum blahblahblah",
    "EventLabel": "#FFF",
    "ENHeadline": "SAL|Men|skinnyhalfrightcampaign|ALL|NA",
    "ENSubline": "",
    "ZHHeadline": "",
    "ZHSubline": ""
  }
]
